{
  "meta": {
    "id": "tmdb:846049",
    "type": "movie",
    "name": "The Dresden Sun",
    "description": "A brilliant, principled mercenary with a traumatic past works with an insider to steal a valued asset from Peredor Corporation called “the sphere”. The C & Earth corporation, vying for global dominance, seeks to find a solution to an otherworldly technology via a scientist’s project. Meanwhile, a financial analyst, who despises his job at the powerful investment firm Mutual One, finds himself caught between deadly corporate rivals, financial fraud, and technological espionage, and is ultimately forced to run from a psychopathic military contractor.",
    "poster": "https://image.tmdb.org/t/p/w500/cwBA8R171aQb2M3Iax80BYvYS1i.jpg",
    "background": "https://image.tmdb.org/t/p/original/fOCHowI9iKaVOND2eZ9LwuvE953.jpg",
    "released": "2026-02-06",
    "imdb": "tt1959374"
  }
}