{
  "meta": {
    "id": "tmdb:1146058",
    "type": "movie",
    "name": "The Pout-Pout Fish",
    "description": "Living on a rundown shipwreck, Mr. Fish one day discovers a hyperactive young sea dragon Pip – who had mistaken his home for a junkyard – pilfering his belongings. The heated argument that ensues leaves both their houses in ruin. But there is hope! Embarking on a seemingly impossible quest in search of the mythical 'Shimmer' to grant them a wish, there’s only one problem: someone else is on the hunt...",
    "poster": "https://image.tmdb.org/t/p/w500/fcDXgGL14qL46It1XOozEjX5Jws.jpg",
    "background": "https://image.tmdb.org/t/p/original/6qQQhhF87Rm1z2TYhXAmoPiEHME.jpg",
    "released": "2026-01-01",
    "imdb": "tt12824390"
  }
}