{
  "meta": {
    "id": "tmdbtv:318421",
    "type": "movie",
    "name": "ONE PIECE: Into the Grand Line: Official Podcast",
    "description": "The Straw Hats take the helm for a deep dive into the making of season 2, featuring candid chats with the cast, crew and Oda himself.",
    "poster": "https://image.tmdb.org/t/p/w500/sF94dv9FYrBdoYrVGiSV2Qx8pvg.jpg",
    "background": "https://image.tmdb.org/t/p/original/wS1xB9um2hEtzXBKqwaghHHiy9x.jpg",
    "released": "2026-03-13",
    "imdb": null
  }
}