{
  "meta": {
    "id": "tmdb:1624183",
    "type": "movie",
    "name": "Blackout",
    "description": "After a nuclear strike devastates California, a group of veterans and criminals trapped in a warehouse must fight to survive marauders, radiation, and each other in a world where the line between good and evil is gone.",
    "poster": "https://image.tmdb.org/t/p/w500/gFy3I3hJeLKKJt8EGpc1ZbGTwoH.jpg",
    "background": "https://image.tmdb.org/t/p/original/3m4jsYrVGx5hZCofSaUd6eNWzXD.jpg",
    "released": "2026-01-27",
    "imdb": "tt34673881"
  }
}