{
  "meta": {
    "id": "tmdb:1631201",
    "type": "movie",
    "name": "Operation Wolf Foster",
    "description": "Once nearly extinct, the critically endangered Mexican wolf is making a comeback - thanks to a bold conservation effort that places captive-born pups into wild dens. Operation Wolf Foster takes you inside this high-stakes recovery program, following the delicate journey of newborn wolves as they’re flown across the country and carefully introduced into the wild, offering hope for the species’ future.",
    "poster": "https://image.tmdb.org/t/p/w500/946lLprFILKl9Ebq9AXGn00oTod.jpg",
    "background": null,
    "released": "2026-04-22",
    "imdb": null
  }
}